setup.py
identity/identity.py
identitylib.egg-info/PKG-INFO
identitylib.egg-info/SOURCES.txt
identitylib.egg-info/dependency_links.txt
identitylib.egg-info/top_level.txt