Metadata-Version: 2.1
Name: identitylib
Version: 1.0.2
Summary: identity function
Home-page: UNKNOWN
Author-email: avtahovfarit@gmail.com
License: UNKNOWN
Platform: UNKNOWN
